pinax/__init__.py
pinax/blog/__init__.py
pinax/blog/admin.py
pinax/blog/apps.py
pinax/blog/conf.py
pinax/blog/context_processors.py
pinax/blog/forms.py
pinax/blog/hooks.py
pinax/blog/managers.py
pinax/blog/models.py
pinax/blog/receivers.py
pinax/blog/signals.py
pinax/blog/urls.py
pinax/blog/utils.py
pinax/blog/views.py
pinax/blog/migrations/0001_initial.py
pinax/blog/migrations/0002_post_state.py
pinax/blog/migrations/0003_auto_20150529_0405.py
pinax/blog/migrations/0004_auto_20150530_1541.py
pinax/blog/migrations/0005_auto_20151218_1733.py
pinax/blog/migrations/0006_auto_20160321_1527.py
pinax/blog/migrations/0007_auto_20161223_1013.py
pinax/blog/migrations/0008_auto_20161223_1013.py
pinax/blog/migrations/0009_auto_20161223_1013.py
pinax/blog/migrations/0010_auto_20161223_1014.py
pinax/blog/migrations/0011_post_image_set.py
pinax/blog/migrations/0012_set_default_imagesets.py
pinax/blog/migrations/0013_imageset_not_null.py
pinax/blog/migrations/0014_migrate_to_pinax_images.py
pinax/blog/migrations/0015_drop_primary_image.py
pinax/blog/migrations/0016_drop_image.py
pinax/blog/migrations/0017_remove_post_tweet_text.py
pinax/blog/migrations/0018_auto_20170213_1035.py
pinax/blog/migrations/0019_conditional_slug_unique.py
pinax/blog/migrations/0020_auto_20171106_2252.py
pinax/blog/migrations/__init__.py
pinax/blog/parsers/__init__.py
pinax/blog/parsers/creole_parser.py
pinax/blog/parsers/markdown_parser.py
pinax/blog/static/js/admin_post_form.js
pinax/blog/templates/pinax/blog/_preview.html
pinax/blog/templates/pinax/blog/atom_entry.xml
pinax/blog/templates/pinax/blog/atom_feed.xml
pinax/blog/templates/pinax/blog/manage_post_create.html
pinax/blog/templates/pinax/blog/manage_post_delete_confirm.html
pinax/blog/templates/pinax/blog/manage_post_list.html
pinax/blog/templates/pinax/blog/manage_post_update.html
pinax/blog/templates/pinax/blog/rss_feed.xml
pinax/blog/templates/pinax/blog/rss_item.xml
pinax/blog/templatetags/__init__.py
pinax_blog-8.0.1.dist-info/AUTHORS
pinax_blog-8.0.1.dist-info/LICENSE
pinax_blog-8.0.1.dist-info/METADATA
pinax_blog-8.0.1.dist-info/WHEEL
pinax_blog-8.0.1.dist-info/top_level.txt
pinax_blog-8.0.1.dist-info/RECORD
