Metadata-Version: 2.1
Name: pinax-blog
Version: 8.0.1
Summary: Blogging app for the Django web framework
Home-page: http://github.com/pinax/pinax-blog/
Author: Pinax Team
Author-email: team@pinaxproject.com
License: MIT
Platform: UNKNOWN
Classifier: Development Status :: 5 - Production/Stable
Classifier: Environment :: Web Environment
Classifier: Framework :: Django
Classifier: Framework :: Django :: 2.2
Classifier: Framework :: Django :: 3.0
Classifier: Intended Audience :: Developers
Classifier: License :: OSI Approved :: MIT License
Classifier: Operating System :: OS Independent
Classifier: Programming Language :: Python
Classifier: Programming Language :: Python :: 3.6
Classifier: Programming Language :: Python :: 3.7
Classifier: Programming Language :: Python :: 3.8
Classifier: Topic :: Software Development :: Libraries :: Python Modules
Requires-Dist: django (>=2.2)
Requires-Dist: django-appconf (>=1.0.1)
Requires-Dist: markdown (==2.6.11)
Requires-Dist: pillow (>=3.0.0)
Requires-Dist: pinax-images (>=3.0.1)
Requires-Dist: pygments (>=2.0.2)
Requires-Dist: pytz (>=2020.1)
